{"tournamentName": "League Two", "date": "Tuesday 12th March", "events": [{"home": {"id": "7sck2yj98lv9ogljofza0c7f9", "fullName": "AFC Wimbledon", "shortName": "Wimbledon", "urn": "urn:bbc:sportsdata:football:team:afc-wimbledon", "runningScores": {"halftime": "1", "fulltime": "2"}, "scoreUnconfirmed": "2", "actions": [{"playerUrn": "urn:bbc:sportsdata:football:player:s-5ipdgq939lvlf15mzzq7t6ga1", "playerName": "Omar Bugiel", "actionType": "goal", "actions": [{"type": "Goal", "typeLabel": {"value": "Goal", "accessible": "Goal"}, "timeLabel": {"value": "33'", "accessible": "33 minutes"}}, {"type": "Goal", "typeLabel": {"value": "Goal", "accessible": "Goal"}, "timeLabel": {"value": "65'", "accessible": "65 minutes"}}]}], "score": "2"}, "away": {"id": "2597fv0oiboak9jyryf3gt39g", "fullName": "Gillingham", "shortName": "Gillingham", "urn": "urn:bbc:sportsdata:football:team:gillingham", "runningScores": {"halftime": "0", "fulltime": "0"}, "scoreUnconfirmed": "0", "actions": [{"playerUrn": "urn:bbc:sportsdata:football:player:s-dtas76j79kkdoxp7nrr2iywut", "playerName": "C. Masterson", "actionType": "card", "actions": [{"type": "Two Yellow Cards", "typeLabel": {"value": "Two Yellow Cards", "accessible": "Two Yellow Cards"}, "timeLabel": {"value": "38'", "accessible": "38 minutes"}}]}], "score": "0"}, "id": "s-ce96duwwiwhppspm142jlin10", "urn": "urn:bbc:sportsdata:football:event:s-ce96duwwiwhppspm142jlin10", "eventGroupingLabel": "England - League Two", "startDateTime": "2024-03-12T19:45:00Z", "tournamentId": "bgen5kjer2ytfp7lo9949t72g", "date": {"iso": "2024-03-12T19:45:00Z", "time": "19:45", "shortDate": "Tue 12 Mar", "longDate": "Tuesday 12th March 2024", "dayOfWeek": "Tue", "day": "12", "month": "March", "shortMonth": "Mar", "year": "2024", "isoDate": "2024-03-12"}, "periodLabel": {"value": "FT", "accessible": "Full time"}, "time": {"accessibleTime": "19:45", "displayTimeUK": "19:45", "timeCertainty": true}, "status": "PostEvent", "statusComment": {"value": "FT", "accessible": "Full time"}, "participants": [{"id": "7sck2yj98lv9ogljofza0c7f9", "urn": "urn:bbc:sportsdata:football:team:afc-wimbledon", "name": {"fullName": "AFC Wimbledon", "shortName": "Wimbledon"}, "score": "2", "halftimeScore": "1", "fulltimeScore": "2", "alignment": "home"}, {"id": "2597fv0oiboak9jyryf3gt39g", "urn": "urn:bbc:sportsdata:football:team:gillingham", "name": {"fullName": "Gillingham", "shortName": "Gillingham"}, "score": "0", "halftimeScore": "0", "fulltimeScore": "0", "alignment": "away"}], "headToHeadDetailLabel": "League Two", "tournament": {"id": "bgen5kjer2ytfp7lo9949t72g", "name": "League Two", "disambiguatedName": "English Football League - League Two", "urn": "urn:bbc:sportsdata:football:tournament:league-two", "thingsGuid": "71d1288c-d1ea-6a4a-bd87-237dbb9e6470"}, "winner": "home", "tipoTopicId": "cgr7999d0jzt", "onwardJourneyLink": "/sport/football/live/cgr7999d0jzt", "accessibleEventSummary": "AFC Wimbledon 2 , Gillingham 0 at Full time"}, {"home": {"id": "2b5k2yusdx2ctd5cdv739p3il", "fullName": "Bradford City", "shortName": "Bradford", "urn": "urn:bbc:sportsdata:football:team:bradford-city", "runningScores": {"halftime": "0", "fulltime": "0"}, "scoreUnconfirmed": "0", "actions": [], "score": "0"}, "away": {"id": "17zuelixesst1z59fwcix2dil", "fullName": "Forest Green Rovers", "shortName": "Forest Green", "urn": "urn:bbc:sportsdata:football:team:forest-green-rovers", "runningScores": {"halftime": "1", "fulltime": "2"}, "scoreUnconfirmed": "2", "actions": [{"playerUrn": "urn:bbc:sportsdata:football:player:s-71xg650qcs8yibhrumgvdejth", "playerName": "C. Doidge", "actionType": "goal", "actions": [{"type": "Goal", "typeLabel": {"value": "Goal", "accessible": "Goal"}, "timeLabel": {"value": "1'", "accessible": "1 minute"}}, {"type": "Penalty", "typeLabel": {"value": "Penalty", "accessible": "Penalty"}, "timeLabel": {"value": "90'+3", "accessible": "90 minutes plus 3"}}]}], "score": "2"}, "id": "s-cej4t178rwslpmz8v7vdhjrbo", "urn": "urn:bbc:sportsdata:football:event:s-cej4t178rwslpmz8v7vdhjrbo", "eventGroupingLabel": "England - League Two", "startDateTime": "2024-03-12T19:45:00Z", "tournamentId": "bgen5kjer2ytfp7lo9949t72g", "date": {"iso": "2024-03-12T19:45:00Z", "time": "19:45", "shortDate": "Tue 12 Mar", "longDate": "Tuesday 12th March 2024", "dayOfWeek": "Tue", "day": "12", "month": "March", "shortMonth": "Mar", "year": "2024", "isoDate": "2024-03-12"}, "periodLabel": {"value": "FT", "accessible": "Full time"}, "time": {"accessibleTime": "19:45", "displayTimeUK": "19:45", "timeCertainty": true}, "status": "PostEvent", "statusComment": {"value": "FT", "accessible": "Full time"}, "participants": [{"id": "2b5k2yusdx2ctd5cdv739p3il", "urn": "urn:bbc:sportsdata:football:team:bradford-city", "name": {"fullName": "Bradford City", "shortName": "Bradford"}, "score": "0", "halftimeScore": "0", "fulltimeScore": "0", "alignment": "home"}, {"id": "17zuelixesst1z59fwcix2dil", "urn": "urn:bbc:sportsdata:football:team:forest-green-rovers", "name": {"fullName": "Forest Green Rovers", "shortName": "Forest Green"}, "score": "2", "halftimeScore": "1", "fulltimeScore": "2", "alignment": "away"}], "headToHeadDetailLabel": "League Two", "tournament": {"id": "bgen5kjer2ytfp7lo9949t72g", "name": "League Two", "disambiguatedName": "English Football League - League Two", "urn": "urn:bbc:sportsdata:football:tournament:league-two", "thingsGuid": "71d1288c-d1ea-6a4a-bd87-237dbb9e6470"}, "winner": "away", "tipoTopicId": "crgvrrr1n0xt", "onwardJourneyLink": "/sport/football/live/crgvrrr1n0xt", "accessibleEventSummary": "Bradford City 0 , Forest Green Rovers 2 at Full time"}, {"home": {"id": "41pv4kcoqzdkswdzqhll8ellb", "fullName": "Crawley Town", "shortName": "Crawley", "urn": "urn:bbc:sportsdata:football:team:crawley-town", "runningScores": {"halftime": "0", "fulltime": "2"}, "scoreUnconfirmed": "2", "actions": [{"playerUrn": "urn:bbc:sportsdata:football:player:s-6719e8qeu0xpu4ac9f67ph7u", "playerName": "K. Lolos", "actionType": "goal", "actions": [{"type": "Goal", "typeLabel": {"value": "Goal", "accessible": "Goal"}, "timeLabel": {"value": "79'", "accessible": "79 minutes"}}]}, {"playerUrn": "urn:bbc:sportsdata:football:player:s-d6yqv7j959j2oefwn5swvkr9w", "playerName": "A. Adeyemo", "actionType": "goal", "actions": [{"type": "Goal", "typeLabel": {"value": "Goal", "accessible": "Goal"}, "timeLabel": {"value": "84'", "accessible": "84 minutes"}}]}], "score": "2"}, "away": {"id": "d3mskb8nk3afyi3tn0gt8kwh8", "fullName": "Notts County", "shortName": "Notts", "urn": "urn:bbc:sportsdata:football:team:notts-county", "runningScores": {"halftime": "1", "fulltime": "1"}, "scoreUnconfirmed": "1", "actions": [{"playerUrn": "urn:bbc:sportsdata:football:player:s-b9zb2ufidxzn2xat28j43bljp", "playerName": "S. Austin", "actionType": "goal", "actions": [{"type": "Goal", "typeLabel": {"value": "Goal", "accessible": "Goal"}, "timeLabel": {"value": "20'", "accessible": "20 minutes"}}]}, {"playerUrn": "urn:bbc:sportsdata:football:player:s-2y1fhmv1aw0ocpu3h0wrfi1d6", "playerName": "S. Robertson", "actionType": "card", "actions": [{"type": "Two Yellow Cards", "typeLabel": {"value": "Two Yellow Cards", "accessible": "Two Yellow Cards"}, "timeLabel": {"value": "72'", "accessible": "72 minutes"}}]}], "score": "1"}, "id": "s-cf55wmmj66nefwwmf4cgz2h3o", "urn": "urn:bbc:sportsdata:football:event:s-cf55wmmj66nefwwmf4cgz2h3o", "eventGroupingLabel": "England - League Two", "startDateTime": "2024-03-12T19:45:00Z", "tournamentId": "bgen5kjer2ytfp7lo9949t72g", "date": {"iso": "2024-03-12T19:45:00Z", "time": "19:45", "shortDate": "Tue 12 Mar", "longDate": "Tuesday 12th March 2024", "dayOfWeek": "Tue", "day": "12", "month": "March", "shortMonth": "Mar", "year": "2024", "isoDate": "2024-03-12"}, "periodLabel": {"value": "FT", "accessible": "Full time"}, "time": {"accessibleTime": "19:45", "displayTimeUK": "19:45", "timeCertainty": true}, "status": "PostEvent", "statusComment": {"value": "FT", "accessible": "Full time"}, "participants": [{"id": "41pv4kcoqzdkswdzqhll8ellb", "urn": "urn:bbc:sportsdata:football:team:crawley-town", "name": {"fullName": "Crawley Town", "shortName": "Crawley"}, "score": "2", "halftimeScore": "0", "fulltimeScore": "2", "alignment": "home"}, {"id": "d3mskb8nk3afyi3tn0gt8kwh8", "urn": "urn:bbc:sportsdata:football:team:notts-county", "name": {"fullName": "Notts County", "shortName": "Notts"}, "score": "1", "halftimeScore": "1", "fulltimeScore": "1", "alignment": "away"}], "headToHeadDetailLabel": "League Two", "tournament": {"id": "bgen5kjer2ytfp7lo9949t72g", "name": "League Two", "disambiguatedName": "English Football League - League Two", "urn": "urn:bbc:sportsdata:football:tournament:league-two", "thingsGuid": "71d1288c-d1ea-6a4a-bd87-237dbb9e6470"}, "winner": "home", "tipoTopicId": "cn0wgggq12nt", "onwardJourneyLink": "/sport/football/live/cn0wgggq12nt", "accessibleEventSummary": "Crawley Town 2 , Notts County 1 at Full time"}, {"home": {"id": "9ze1c55gavzeg6vw37ca1banb", "fullName": "Crewe Alexandra", "shortName": "Crewe", "urn": "urn:bbc:sportsdata:football:team:crewe-alexandra", "runningScores": {"halftime": "0", "fulltime": "1"}, "scoreUnconfirmed": "1", "actions": [{"playerUrn": "urn:bbc:sportsdata:football:player:s-cfctx4jjyzrqgeu1kcyt60f10", "playerName": "E. Nevitt", "actionType": "goal", "actions": [{"type": "Goal", "typeLabel": {"value": "Goal", "accessible": "Goal"}, "timeLabel": {"value": "71'", "accessible": "71 minutes"}}]}], "score": "1"}, "away": {"id": "868eewpas8ksqiyprnczkpran", "fullName": "Sutton United", "shortName": "Sutton Utd", "urn": "urn:bbc:sportsdata:football:team:sutton-united", "runningScores": {"halftime": "0", "fulltime": "0"}, "scoreUnconfirmed": "0", "actions": [], "score": "0"}, "id": "s-cff2p44o1ftl7xms9o7tasr2s", "urn": "urn:bbc:sportsdata:football:event:s-cff2p44o1ftl7xms9o7tasr2s", "eventGroupingLabel": "England - League Two", "startDateTime": "2024-03-12T19:45:00Z", "tournamentId": "bgen5kjer2ytfp7lo9949t72g", "date": {"iso": "2024-03-12T19:45:00Z", "time": "19:45", "shortDate": "Tue 12 Mar", "longDate": "Tuesday 12th March 2024", "dayOfWeek": "Tue", "day": "12", "month": "March", "shortMonth": "Mar", "year": "2024", "isoDate": "2024-03-12"}, "periodLabel": {"value": "FT", "accessible": "Full time"}, "time": {"accessibleTime": "19:45", "displayTimeUK": "19:45", "timeCertainty": true}, "status": "PostEvent", "statusComment": {"value": "FT", "accessible": "Full time"}, "participants": [{"id": "9ze1c55gavzeg6vw37ca1banb", "urn": "urn:bbc:sportsdata:football:team:crewe-alexandra", "name": {"fullName": "Crewe Alexandra", "shortName": "Crewe"}, "score": "1", "halftimeScore": "0", "fulltimeScore": "1", "alignment": "home"}, {"id": "868eewpas8ksqiyprnczkpran", "urn": "urn:bbc:sportsdata:football:team:sutton-united", "name": {"fullName": "Sutton United", "shortName": "Sutton Utd"}, "score": "0", "halftimeScore": "0", "fulltimeScore": "0", "alignment": "away"}], "headToHeadDetailLabel": "League Two", "tournament": {"id": "bgen5kjer2ytfp7lo9949t72g", "name": "League Two", "disambiguatedName": "English Football League - League Two", "urn": "urn:bbc:sportsdata:football:tournament:league-two", "thingsGuid": "71d1288c-d1ea-6a4a-bd87-237dbb9e6470"}, "winner": "home", "tipoTopicId": "cy9zppp1vv0t", "onwardJourneyLink": "/sport/football/live/cy9zppp1vv0t", "accessibleEventSummary": "Crewe Alexandra 1 , Sutton United 0 at Full time"}, {"home": {"id": "6ipyteigr21t78l6fro3ig10j", "fullName": "Grimsby Town", "shortName": "Grimsby", "urn": "urn:bbc:sportsdata:football:team:grimsby-town", "runningScores": {"halftime": "1", "fulltime": "1"}, "scoreUnconfirmed": "1", "actions": [{"playerUrn": "urn:bbc:sportsdata:football:player:s-6w27tc2ri3dzrwh9bgoliyexg", "playerName": "J. Obikwu", "actionType": "goal", "actions": [{"type": "Goal", "typeLabel": {"value": "Goal", "accessible": "Goal"}, "timeLabel": {"value": "33'", "accessible": "33 minutes"}}]}], "score": "1"}, "away": {"id": "8w89tsles26jm12aoelwvlttt", "fullName": "Milton Keynes Dons", "shortName": "MK Dons", "urn": "urn:bbc:sportsdata:football:team:milton-keynes-dons", "runningScores": {"halftime": "0", "fulltime": "0"}, "scoreUnconfirmed": "0", "actions": [], "score": "0"}, "id": "s-cfp2sq571r5a2atbwp4r586xg", "urn": "urn:bbc:sportsdata:football:event:s-cfp2sq571r5a2atbwp4r586xg", "eventGroupingLabel": "England - League Two", "startDateTime": "2024-03-12T19:45:00Z", "tournamentId": "bgen5kjer2ytfp7lo9949t72g", "date": {"iso": "2024-03-12T19:45:00Z", "time": "19:45", "shortDate": "Tue 12 Mar", "longDate": "Tuesday 12th March 2024", "dayOfWeek": "Tue", "day": "12", "month": "March", "shortMonth": "Mar", "year": "2024", "isoDate": "2024-03-12"}, "periodLabel": {"value": "FT", "accessible": "Full time"}, "time": {"accessibleTime": "19:45", "displayTimeUK": "19:45", "timeCertainty": true}, "status": "PostEvent", "statusComment": {"value": "FT", "accessible": "Full time"}, "participants": [{"id": "6ipyteigr21t78l6fro3ig10j", "urn": "urn:bbc:sportsdata:football:team:grimsby-town", "name": {"fullName": "Grimsby Town", "shortName": "Grimsby"}, "score": "1", "halftimeScore": "1", "fulltimeScore": "1", "alignment": "home"}, {"id": "8w89tsles26jm12aoelwvlttt", "urn": "urn:bbc:sportsdata:football:team:milton-keynes-dons", "name": {"fullName": "Milton Keynes Dons", "shortName": "MK Dons"}, "score": "0", "halftimeScore": "0", "fulltimeScore": "0", "alignment": "away"}], "headToHeadDetailLabel": "League Two", "tournament": {"id": "bgen5kjer2ytfp7lo9949t72g", "name": "League Two", "disambiguatedName": "English Football League - League Two", "urn": "urn:bbc:sportsdata:football:tournament:league-two", "thingsGuid": "71d1288c-d1ea-6a4a-bd87-237dbb9e6470"}, "winner": "home", "tipoTopicId": "crg06661d3gt", "onwardJourneyLink": "/sport/football/live/crg06661d3gt", "accessibleEventSummary": "Grimsby Town 1 , Milton Keynes Dons 0 at Full time"}, {"home": {"id": "bewbbriuwh3i7a2zn19e6d0v4", "fullName": "Newport County", "shortName": "Newport", "urn": "urn:bbc:sportsdata:football:team:newport-county", "runningScores": {"halftime": "2", "fulltime": "5"}, "scoreUnconfirmed": "5", "actions": [{"playerUrn": "urn:bbc:sportsdata:football:player:s-56x6wo05188a1eiuqjcjtl1p1", "playerName": "A. Wildig", "actionType": "goal", "actions": [{"type": "Goal", "typeLabel": {"value": "Goal", "accessible": "Goal"}, "timeLabel": {"value": "12'", "accessible": "12 minutes"}}, {"type": "Goal", "typeLabel": {"value": "Goal", "accessible": "Goal"}, "timeLabel": {"value": "54'", "accessible": "54 minutes"}}]}, {"playerUrn": "urn:bbc:sportsdata:football:player:s-8w3ph3ghxo55vghnzvzk1txpl", "playerName": "A. Lewis", "actionType": "goal", "actions": [{"type": "Goal", "typeLabel": {"value": "Goal", "accessible": "Goal"}, "timeLabel": {"value": "18'", "accessible": "18 minutes"}}]}, {"playerUrn": "urn:bbc:sportsdata:football:player:s-2k3y4x681f46nqbqxxb2kfl5h", "playerName": "H. Charsley", "actionType": "goal", "actions": [{"type": "Goal", "typeLabel": {"value": "Goal", "accessible": "Goal"}, "timeLabel": {"value": "78'", "accessible": "78 minutes"}}]}, {"playerUrn": "urn:bbc:sportsdata:football:player:s-65s454koas239vtre3amccavo", "playerName": "S. Palmer-Houlden", "actionType": "goal", "actions": [{"type": "Goal", "typeLabel": {"value": "Goal", "accessible": "Goal"}, "timeLabel": {"value": "90'+7", "accessible": "90 minutes plus 7"}}]}], "score": "5"}, "away": {"id": "8xeuwzxnm7hdlbjjuezgfkz3w", "fullName": "Morecambe", "shortName": "Morecambe", "urn": "urn:bbc:sportsdata:football:team:morecambe", "runningScores": {"halftime": "1", "fulltime": "3"}, "scoreUnconfirmed": "3", "actions": [{"playerUrn": "urn:bbc:sportsdata:football:player:s-156hlg4mne48ct15fm5qtpjo5", "playerName": "G. Edwards", "actionType": "goal", "actions": [{"type": "Goal", "typeLabel": {"value": "Goal", "accessible": "Goal"}, "timeLabel": {"value": "31'", "accessible": "31 minutes"}}, {"type": "Goal", "typeLabel": {"value": "Goal", "accessible": "Goal"}, "timeLabel": {"value": "74'", "accessible": "74 minutes"}}]}, {"playerUrn": "urn:bbc:sportsdata:football:player:s-1pt1yc4fl9oxxsaoeq1cm3xzp", "playerName": "C. Stokes", "actionType": "goal", "actions": [{"type": "Goal", "typeLabel": {"value": "Goal", "accessible": "Goal"}, "timeLabel": {"value": "70'", "accessible": "70 minutes"}}]}], "score": "3"}, "id": "s-cfz17wuwconl3e5v2h29ld8no", "urn": "urn:bbc:sportsdata:football:event:s-cfz17wuwconl3e5v2h29ld8no", "eventGroupingLabel": "England - League Two", "startDateTime": "2024-03-12T19:45:00Z", "tournamentId": "bgen5kjer2ytfp7lo9949t72g", "date": {"iso": "2024-03-12T19:45:00Z", "time": "19:45", "shortDate": "Tue 12 Mar", "longDate": "Tuesday 12th March 2024", "dayOfWeek": "Tue", "day": "12", "month": "March", "shortMonth": "Mar", "year": "2024", "isoDate": "2024-03-12"}, "periodLabel": {"value": "FT", "accessible": "Full time"}, "time": {"accessibleTime": "19:45", "displayTimeUK": "19:45", "timeCertainty": true}, "status": "PostEvent", "statusComment": {"value": "FT", "accessible": "Full time"}, "participants": [{"id": "bewbbriuwh3i7a2zn19e6d0v4", "urn": "urn:bbc:sportsdata:football:team:newport-county", "name": {"fullName": "Newport County", "shortName": "Newport"}, "score": "5", "halftimeScore": "2", "fulltimeScore": "5", "alignment": "home"}, {"id": "8xeuwzxnm7hdlbjjuezgfkz3w", "urn": "urn:bbc:sportsdata:football:team:morecambe", "name": {"fullName": "Morecambe", "shortName": "Morecambe"}, "score": "3", "halftimeScore": "1", "fulltimeScore": "3", "alignment": "away"}], "headToHeadDetailLabel": "League Two", "tournament": {"id": "bgen5kjer2ytfp7lo9949t72g", "name": "League Two", "disambiguatedName": "English Football League - League Two", "urn": "urn:bbc:sportsdata:football:tournament:league-two", "thingsGuid": "71d1288c-d1ea-6a4a-bd87-237dbb9e6470"}, "winner": "home", "tipoTopicId": "c9edxxx5p4zt", "onwardJourneyLink": "/sport/football/live/c9edxxx5p4zt", "accessibleEventSummary": "Newport County 5 , Morecambe 3 at Full time"}, {"home": {"id": "9ws3x82yqn7svjq6onvtunpst", "fullName": "Swindon Town", "shortName": "Swindon", "urn": "urn:bbc:sportsdata:football:team:swindon-town", "runningScores": {"halftime": "0", "fulltime": "1"}, "scoreUnconfirmed": "1", "actions": [{"playerUrn": "urn:bbc:sportsdata:football:player:s-ech3uul4ir5vnsylgfavbal7t", "playerName": "A. Drinan", "actionType": "goal", "actions": [{"type": "Goal", "typeLabel": {"value": "Goal", "accessible": "Goal"}, "timeLabel": {"value": "47'", "accessible": "47 minutes"}}]}], "score": "1"}, "away": {"id": "5qwskbjpa17fvmtuu5qijy7cz", "fullName": "Accrington Stanley", "shortName": "Accrington", "urn": "urn:bbc:sportsdata:football:team:accrington-stanley", "runningScores": {"halftime": "0", "fulltime": "2"}, "scoreUnconfirmed": "2", "actions": [{"playerUrn": "urn:bbc:sportsdata:football:player:s-1vigb3e3dsxufbtvt4ed48e09", "playerName": "J. Nolan", "actionType": "goal", "actions": [{"type": "Penalty", "typeLabel": {"value": "Penalty", "accessible": "Penalty"}, "timeLabel": {"value": "57'", "accessible": "57 minutes"}}]}, {"playerUrn": "urn:bbc:sportsdata:football:player:s-vkag8cx29v1b5wetozm6rp5g", "playerName": "A. Henderson", "actionType": "goal", "actions": [{"type": "Goal", "typeLabel": {"value": "Goal", "accessible": "Goal"}, "timeLabel": {"value": "82'", "accessible": "82 minutes"}}]}], "score": "2"}, "id": "s-cgivi6qmkjawebxqpsf2jrjf8", "urn": "urn:bbc:sportsdata:football:event:s-cgivi6qmkjawebxqpsf2jrjf8", "eventGroupingLabel": "England - League Two", "startDateTime": "2024-03-12T19:45:00Z", "tournamentId": "bgen5kjer2ytfp7lo9949t72g", "date": {"iso": "2024-03-12T19:45:00Z", "time": "19:45", "shortDate": "Tue 12 Mar", "longDate": "Tuesday 12th March 2024", "dayOfWeek": "Tue", "day": "12", "month": "March", "shortMonth": "Mar", "year": "2024", "isoDate": "2024-03-12"}, "periodLabel": {"value": "FT", "accessible": "Full time"}, "time": {"accessibleTime": "19:45", "displayTimeUK": "19:45", "timeCertainty": true}, "status": "PostEvent", "statusComment": {"value": "FT", "accessible": "Full time"}, "participants": [{"id": "9ws3x82yqn7svjq6onvtunpst", "urn": "urn:bbc:sportsdata:football:team:swindon-town", "name": {"fullName": "Swindon Town", "shortName": "Swindon"}, "score": "1", "halftimeScore": "0", "fulltimeScore": "1", "alignment": "home"}, {"id": "5qwskbjpa17fvmtuu5qijy7cz", "urn": "urn:bbc:sportsdata:football:team:accrington-stanley", "name": {"fullName": "Accrington Stanley", "shortName": "Accrington"}, "score": "2", "halftimeScore": "0", "fulltimeScore": "2", "alignment": "away"}], "headToHeadDetailLabel": "League Two", "tournament": {"id": "bgen5kjer2ytfp7lo9949t72g", "name": "League Two", "disambiguatedName": "English Football League - League Two", "urn": "urn:bbc:sportsdata:football:tournament:league-two", "thingsGuid": "71d1288c-d1ea-6a4a-bd87-237dbb9e6470"}, "winner": "away", "tipoTopicId": "cv2y6660p40t", "onwardJourneyLink": "/sport/football/live/cv2y6660p40t", "accessibleEventSummary": "Swindon Town 1 , Accrington Stanley 2 at Full time"}, {"home": {"id": "9j48z9ohucqbzpneoghrgwevs", "fullName": "Tranmere Rovers", "shortName": "Tranmere", "urn": "urn:bbc:sportsdata:football:team:tranmere-rovers", "runningScores": {"halftime": "1", "fulltime": "2"}, "scoreUnconfirmed": "2", "actions": [{"playerUrn": "urn:bbc:sportsdata:football:player:s-693vankfkq50hufuwcz7hu8r9", "playerName": "R. Hendry", "actionType": "goal", "actions": [{"type": "Goal", "typeLabel": {"value": "Goal", "accessible": "Goal"}, "timeLabel": {"value": "12'", "accessible": "12 minutes"}}]}, {"playerUrn": "urn:bbc:sportsdata:football:player:s-8wnfkmvldy46l2i068v20onpw", "playerName": "R. Apter", "actionType": "goal", "actions": [{"type": "Goal", "typeLabel": {"value": "Goal", "accessible": "Goal"}, "timeLabel": {"value": "56'", "accessible": "56 minutes"}}]}], "score": "2"}, "away": {"id": "4hcdmgl41o4blqpbeelu56h7y", "fullName": "Mansfield Town", "shortName": "Mansfield Town", "urn": "urn:bbc:sportsdata:football:team:mansfield-town", "runningScores": {"halftime": "1", "fulltime": "1"}, "scoreUnconfirmed": "1", "actions": [{"playerUrn": "urn:bbc:sportsdata:football:player:s-d4t4cmj2j1jvr89yp68x80k8a", "playerName": "W. Swan", "actionType": "goal", "actions": [{"type": "Goal", "typeLabel": {"value": "Goal", "accessible": "Goal"}, "timeLabel": {"value": "39'", "accessible": "39 minutes"}}]}], "score": "1"}, "id": "s-cgsr5rs4ol0jnieq01ijgxxxw", "urn": "urn:bbc:sportsdata:football:event:s-cgsr5rs4ol0jnieq01ijgxxxw", "eventGroupingLabel": "England - League Two", "startDateTime": "2024-03-12T19:45:00Z", "tournamentId": "bgen5kjer2ytfp7lo9949t72g", "date": {"iso": "2024-03-12T19:45:00Z", "time": "19:45", "shortDate": "Tue 12 Mar", "longDate": "Tuesday 12th March 2024", "dayOfWeek": "Tue", "day": "12", "month": "March", "shortMonth": "Mar", "year": "2024", "isoDate": "2024-03-12"}, "periodLabel": {"value": "FT", "accessible": "Full time"}, "time": {"accessibleTime": "19:45", "displayTimeUK": "19:45", "timeCertainty": true}, "status": "PostEvent", "statusComment": {"value": "FT", "accessible": "Full time"}, "participants": [{"id": "9j48z9ohucqbzpneoghrgwevs", "urn": "urn:bbc:sportsdata:football:team:tranmere-rovers", "name": {"fullName": "Tranmere Rovers", "shortName": "Tranmere"}, "score": "2", "halftimeScore": "1", "fulltimeScore": "2", "alignment": "home"}, {"id": "4hcdmgl41o4blqpbeelu56h7y", "urn": "urn:bbc:sportsdata:football:team:mansfield-town", "name": {"fullName": "Mansfield Town", "shortName": "Mansfield Town"}, "score": "1", "halftimeScore": "1", "fulltimeScore": "1", "alignment": "away"}], "headToHeadDetailLabel": "League Two", "tournament": {"id": "bgen5kjer2ytfp7lo9949t72g", "name": "League Two", "disambiguatedName": "English Football League - League Two", "urn": "urn:bbc:sportsdata:football:tournament:league-two", "thingsGuid": "71d1288c-d1ea-6a4a-bd87-237dbb9e6470"}, "winner": "home", "tipoTopicId": "cjl4zzz0rzjt", "onwardJourneyLink": "/sport/football/live/cjl4zzz0rzjt", "accessibleEventSummary": "Tranmere Rovers 2 , Mansfield Town 1 at Full time"}, {"home": {"id": "1tev1lioyfaxbk2uod5uekzyj", "fullName": "Walsall", "shortName": "Walsall", "urn": "urn:bbc:sportsdata:football:team:walsall", "runningScores": {"halftime": "1", "fulltime": "1"}, "scoreUnconfirmed": "1", "actions": [{"playerUrn": "urn:bbc:sportsdata:football:player:s-8athiwq48cy6lo92wwge1vbh1", "playerName": "R. Menayese", "actionType": "goal", "actions": [{"type": "Goal", "typeLabel": {"value": "Goal", "accessible": "Goal"}, "timeLabel": {"value": "38'", "accessible": "38 minutes"}}]}], "score": "1"}, "away": {"id": "2h0f9b45mwop10akb6bp7qx3", "fullName": "Barrow", "shortName": "Barrow", "urn": "urn:bbc:sportsdata:football:team:barrow", "runningScores": {"halftime": "0", "fulltime": "1"}, "scoreUnconfirmed": "1", "actions": [{"playerUrn": "urn:bbc:sportsdata:football:player:s-xrsjebr9vtuzq0hg7dd8ysix", "playerName": "D. Campbell", "actionType": "goal", "actions": [{"type": "Penalty", "typeLabel": {"value": "Penalty", "accessible": "Penalty"}, "timeLabel": {"value": "53'", "accessible": "53 minutes"}}]}], "score": "1"}, "id": "s-ch2obmn9salto1xpio3dvrrbo", "urn": "urn:bbc:sportsdata:football:event:s-ch2obmn9salto1xpio3dvrrbo", "eventGroupingLabel": "England - League Two", "startDateTime": "2024-03-12T19:45:00Z", "tournamentId": "bgen5kjer2ytfp7lo9949t72g", "date": {"iso": "2024-03-12T19:45:00Z", "time": "19:45", "shortDate": "Tue 12 Mar", "longDate": "Tuesday 12th March 2024", "dayOfWeek": "Tue", "day": "12", "month": "March", "shortMonth": "Mar", "year": "2024", "isoDate": "2024-03-12"}, "periodLabel": {"value": "FT", "accessible": "Full time"}, "time": {"accessibleTime": "19:45", "displayTimeUK": "19:45", "timeCertainty": true}, "status": "PostEvent", "statusComment": {"value": "FT", "accessible": "Full time"}, "participants": [{"id": "1tev1lioyfaxbk2uod5uekzyj", "urn": "urn:bbc:sportsdata:football:team:walsall", "name": {"fullName": "Walsall", "shortName": "Walsall"}, "score": "1", "halftimeScore": "1", "fulltimeScore": "1", "alignment": "home"}, {"id": "2h0f9b45mwop10akb6bp7qx3", "urn": "urn:bbc:sportsdata:football:team:barrow", "name": {"fullName": "Barrow", "shortName": "Barrow"}, "score": "1", "halftimeScore": "0", "fulltimeScore": "1", "alignment": "away"}], "headToHeadDetailLabel": "League Two", "tournament": {"id": "bgen5kjer2ytfp7lo9949t72g", "name": "League Two", "disambiguatedName": "English Football League - League Two", "urn": "urn:bbc:sportsdata:football:tournament:league-two", "thingsGuid": "71d1288c-d1ea-6a4a-bd87-237dbb9e6470"}, "winner": "draw", "tipoTopicId": "cyxznnn1yvzt", "onwardJourneyLink": "/sport/football/live/cyxznnn1yvzt", "accessibleEventSummary": "Walsall 1 , Barrow 1 at Full time"}, {"home": {"id": "206vnsjv8ho5kpf88y0u2gaic", "fullName": "Wrexham", "shortName": "Wrexham", "urn": "urn:bbc:sportsdata:football:team:wrexham", "runningScores": {"halftime": "0", "fulltime": "0"}, "scoreUnconfirmed": "0", "actions": [], "score": "0"}, "away": {"id": "bkzx43uwodxey51ivfvbqf37g", "fullName": "Harrogate Town", "shortName": "Harrogate", "urn": "urn:bbc:sportsdata:football:team:harrogate-town", "runningScores": {"halftime": "0", "fulltime": "0"}, "scoreUnconfirmed": "0", "actions": [], "score": "0"}, "id": "s-chcpelu3m260sgs4bz1m9sduc", "urn": "urn:bbc:sportsdata:football:event:s-chcpelu3m260sgs4bz1m9sduc", "eventGroupingLabel": "England - League Two", "startDateTime": "2024-03-12T19:45:00Z", "tournamentId": "bgen5kjer2ytfp7lo9949t72g", "date": {"iso": "2024-03-12T19:45:00Z", "time": "19:45", "shortDate": "Tue 12 Mar", "longDate": "Tuesday 12th March 2024", "dayOfWeek": "Tue", "day": "12", "month": "March", "shortMonth": "Mar", "year": "2024", "isoDate": "2024-03-12"}, "periodLabel": {"value": "FT", "accessible": "Full time"}, "time": {"accessibleTime": "19:45", "displayTimeUK": "19:45", "timeCertainty": true}, "status": "PostEvent", "statusComment": {"value": "FT", "accessible": "Full time"}, "participants": [{"id": "206vnsjv8ho5kpf88y0u2gaic", "urn": "urn:bbc:sportsdata:football:team:wrexham", "name": {"fullName": "Wrexham", "shortName": "Wrexham"}, "score": "0", "halftimeScore": "0", "fulltimeScore": "0", "alignment": "home"}, {"id": "bkzx43uwodxey51ivfvbqf37g", "urn": "urn:bbc:sportsdata:football:team:harrogate-town", "name": {"fullName": "Harrogate Town", "shortName": "Harrogate"}, "score": "0", "halftimeScore": "0", "fulltimeScore": "0", "alignment": "away"}], "headToHeadDetailLabel": "League Two", "tournament": {"id": "bgen5kjer2ytfp7lo9949t72g", "name": "League Two", "disambiguatedName": "English Football League - League Two", "urn": "urn:bbc:sportsdata:football:tournament:league-two", "thingsGuid": "71d1288c-d1ea-6a4a-bd87-237dbb9e6470"}, "winner": "draw", "tipoTopicId": "clkmvvvjzvkt", "onwardJourneyLink": "/sport/football/live/clkmvvvjzvkt", "accessibleEventSummary": "Wrexham 0 , Harrogate Town 0 at Full time"}], "url": "https://www.bbc.co.uk/sport/football/league-two/scores-fixtures"}