{"displayLabel": null, "secondaryGroups": [{"displayLabel": "League Two", "events": [{"home": {"id": "9j48z9ohucqbzpneoghrgwevs", "fullName": "Tranmere Rovers", "shortName": "Tranmere", "urn": "urn:bbc:sportsdata:football:team:tranmere-rovers", "runningScores": {"halftime": "0", "fulltime": "1"}, "scoreUnconfirmed": "1", "actions": [{"playerUrn": "urn:bbc:sportsdata:football:player:s-7xr6yeu0yevkshdqj9acwmrit", "playerName": "C. Jennings", "actionType": "goal", "actions": [{"type": "Goal", "typeLabel": {"value": "Goal", "accessible": "Goal"}, "timeLabel": {"value": "90'+3", "accessible": "90 minutes plus 3"}}]}], "score": "1"}, "away": {"id": "2zyk4fq2f0kh5p366q9y62vny", "fullName": "Chesterfield", "shortName": "Chesterfield", "urn": "urn:bbc:sportsdata:football:team:chesterfield", "runningScores": {"halftime": "1", "fulltime": "1"}, "scoreUnconfirmed": "1", "actions": [{"playerUrn": "urn:bbc:sportsdata:football:player:s-4k6nbdla5or3o2bdgfal2c355", "playerName": "O. Patrick", "actionType": "goal", "actions": [{"type": "Own Goal", "typeLabel": {"value": "Own Goal", "accessible": "Own Goal"}, "timeLabel": {"value": "12'", "accessible": "12 minutes"}}]}], "score": "1"}, "id": "s-abnc059yevr44o76ar02ucgt0", "urn": "urn:bbc:sportsdata:football:event:s-abnc059yevr44o76ar02ucgt0", "eventGroupingLabel": "England - League Two", "startDateTime": "2025-10-25T14:00:00Z", "tournamentId": "bgen5kjer2ytfp7lo9949t72g", "date": {"iso": "2025-10-25T14:00:00Z", "time": "15:00", "shortDate": "Sat 25 Oct", "longDate": "Saturday 25th October 2025", "dayOfWeek": "Sat", "day": "25", "month": "October", "shortMonth": "Oct", "year": "2025", "isoDate": "2025-10-25"}, "periodLabel": {"value": "FT", "accessible": "Full time"}, "time": {"accessibleTime": "15:00", "displayTimeUK": "15:00", "timeCertainty": true}, "status": "PostEvent", "statusComment": {"value": "FT", "accessible": "Full time"}, "participants": [{"id": "9j48z9ohucqbzpneoghrgwevs", "urn": "urn:bbc:sportsdata:football:team:tranmere-rovers", "name": {"fullName": "Tranmere Rovers", "shortName": "Tranmere"}, "score": "1", "halftimeScore": "0", "fulltimeScore": "1", "alignment": "home"}, {"id": "2zyk4fq2f0kh5p366q9y62vny", "urn": "urn:bbc:sportsdata:football:team:chesterfield", "name": {"fullName": "Chesterfield", "shortName": "Chesterfield"}, "score": "1", "halftimeScore": "1", "fulltimeScore": "1", "alignment": "away"}], "headToHeadDetailLabel": "League Two", "tournament": {"id": "bgen5kjer2ytfp7lo9949t72g", "name": "League Two", "disambiguatedName": "League Two", "urn": "urn:bbc:sportsdata:football:tournament:league-two", "thingsGuid": "71d1288c-d1ea-6a4a-bd87-237dbb9e6470"}, "winner": "draw", "tipoTopicId": "cj0e23lq50mt", "onwardJourneyLink": "/sport/football/live/cj0e23lq50mt", "accessibleEventSummary": "Tranmere Rovers 1 , Chesterfield 1 at Full time", "hasStandings": true}]}]}